notifly_client/__init__.py
notifly_client/client.py
notifly_client-0.1.2.dist-info/METADATA
notifly_client-0.1.2.dist-info/WHEEL
notifly_client-0.1.2.dist-info/top_level.txt
notifly_client-0.1.2.dist-info/RECORD
