Metadata-Version: 2.1
Name: notifly-client
Version: 0.1.2
Summary: Bindings for the Notifly API
Home-page: UNKNOWN
Author: Felipe Lacerda
License: UNKNOWN
Platform: UNKNOWN
Requires-Python: >=3.7
